ohcs/__init__.py
ohcs/py.typed
ohcs/common/__init__.py
ohcs/common/daemon.py
ohcs/common/executor.py
ohcs/common/logging_config.py
ohcs/common/stats.py
ohcs/common/stats_logger.py
ohcs/common/utils.py
ohcs/lcm/LifecycleManagement.pyi
ohcs/lcm/__init__.py
ohcs/lcm/__main__.py
ohcs/lcm/api.py
ohcs/lcm/config.py
ohcs/lcm/examples/DemoStore.py
ohcs/lcm/examples/__init__.py
ohcs/lcm/examples/lcm_plugin.py
ohcs/lcm/examples/tutorial.plan.yml
ohcs/lcm/pair/__init__.py
ohcs/lcm/pair/default_config.yml
ohcs/lcm/pair/main.py
ohcs/lcm/pair/pairing.example.properties
ohcs/lcm/pair/pairing.plan.yml
ohcs/lcm/plugin/__init__.py
ohcs/lcm/plugin/simulator.py
ohcs/lcm/plugin/terraform.py
ohcs/lcm/plugin/tf_helper.py
ohcs/lcm/serve/__init__.py
ohcs/lcm/serve/adapter.py
ohcs/lcm/serve/factory.py
ohcs/lcm/serve/main.py
ohcs/lcm/verify/__init__.py
ohcs/lcm/verify/akka.plan.yml
ohcs/lcm/verify/helper.py
ohcs/lcm/verify/plugin-simulator.json
ohcs/lcm/verify/steps.py
ohcs/rte/__init__.py
ohcs/rte/ezhub.py
ohcs/rte/mqtt_config.py
ohcs/rte/protocol.py
ohcs/rte/rte.py
ohcs-1.0.36.dist-info/METADATA
ohcs-1.0.36.dist-info/WHEEL
ohcs-1.0.36.dist-info/entry_points.txt
ohcs-1.0.36.dist-info/top_level.txt
ohcs-1.0.36.dist-info/RECORD
